pydapt
