Metadata-Version: 2.1
Name: pydapt
Version: 0.3
Summary: Ruby's OpenStruct for python
Home-page: https://github.com/dev-prakhar/pydapt
Author: Prakhar Shrivastava
Author-email: prakhars1996@gmail.com
License: UNKNOWN
Platform: UNKNOWN
Classifier: Programming Language :: Python :: 3
Classifier: License :: OSI Approved :: MIT License
Classifier: Operating System :: OS Independent
